{
  "evenements": {
    "2025-01-16": {
      "titre": "Sortie du 16/01/2025",
      "jeux": [
        {
          "id": "16012025-1",
          "titre": "Donkey Kong Country Return HD",
          "description": "Version HD de Donkey Kong Country Return sorti précedemment sur Wii",
          "plateformes": ["Switch"]
        },
        {
          "id": "16012025-2",
          "titre": "Astebros",
          "description": "2ème jeu du studio français NEOFID après le très réussi Demons of Asteborg.",
          "plateformes": ["PS5"]
        }
      ]
    },
    "2025-01-17": {
      "titre": "Sortie du 17/01/2025",
      "jeux": [
        {
          "id": "17012025-1",
          "titre": "Tales of Graces f Remastered",
          "description": "Le remaster de Tales of Graces f sorti à l'époque sur PS3",
          "plateformes": ["PS5", "Switch"]
        }
      ]
    },
    "2025-02-27": {
      "titre": "Sortie du 27/02/2025",
      "jeux": [
        {
          "id": "27022025-1",
          "titre": "Him, The smile & Bloom",
          "description": "",
          "plateformes": ["Switch"]
        }
      ]
    },
    "2025-03-06": {
      "titre": "Sortie du 06/03/2025",
      "jeux": [
        {
          "id": "06032025-1",
          "titre": "Suikoden 1&2 HD remaster Gate Rune & Dunnan Unification Wars ",
          "description": "Le remaster des deux premiers Suikoden sortis sur PS1.",
          "plateformes": ["PS5", "Switch", "Xbox x"]
        }
      ]
    },
    "2025-03-13": {
      "titre": "Sortie du 13/03/2025",
      "jeux": [
        {
          "id": "13032025-1",
          "titre": "Beyond the ice palace 2",
          "description": "",
          "plateformes": ["PS5", "Switch"]
        }
      ]
    },
    "2025-03-20": {
      "titre": "Sortie du 20/03/2025",
      "jeux": [
        {
          "id": "20032025-1",
          "titre": "Xenoblade X Définitive édition",
          "description": "L'édition définitive du Xenoblade sortie sur WII U",
          "plateformes": ["Switch"]
        }
      ]
    },
    "2025-03-21": {
      "titre": "Sortie du 21/03/2025",
      "jeux": [
        {
          "id": "21032025-1",
          "titre": "The messenger",
          "description": "",
          "plateformes": ["PS5, Switch"]
        }
      ]
    },
    "2025-04-18": {
      "titre": "Sortie du 18/04/2025",
      "jeux": [
        {
          "id": "18042025-1",
          "titre": "Lunar Remastered Colllection",
          "description": "Versions remasterisées des JRPG Lunar : Silver Star Story et Lunar 2 : Eternal Blue",
          "plateformes": ["PS4", "Switch"]
        }
      ]
    },
    "2025-07-17": {
      "titre": "Sortie du 17/07/2025",
      "jeux": [
        {
          "id": "17072025-1",
          "titre": "Bustafellows Season 2",
          "description": "",
          "plateformes": ["Switch"]
        }
      ]
    },
    "2025-07-25": {
      "titre": "Sortie du 25/07/2025",
      "jeux": [
        {
          "id": "25072025-1",
          "titre": "Les chevaliers de Baphomet Reforged",
          "description": "Remake du célèbre point & click sortie sur PS1 et PC dans les années 90.",
          "plateformes": ["PS5, Switch, Xbox one/S/X"]
        }
      ]
    }
  }
}
